[
    {
        "uid": "tTTtLT1kFAVblNdHhiZwOeWrPa03",
        "username": "blair3003",
        "email": "blair@forthdev.com",
        "displayName": "Blair",
        "createdAt": "2023-10-26T10:23:27.273Z"
    },
    {
        "uid": "40d1e569c3df59f8a10e",
        "username": "jasmine595",
        "email": "jasmine@forthdev.com",
        "displayName": "Jasmine",
        "createdAt": "2023-10-26T10:23:27.273Z"
    },
    {
        "uid": "b4Cu1FRwdkOxvyNFuu2C1rcuQSF3",
        "username": "BlairGoogle",
        "email": "blair3003@gmail.com",
        "displayName": "Blair Google",
        "createdAt": "2023-10-26T10:23:27.273Z"
    }
]